pymole/__init__.py
pymole/backend.py
pymole/base.py
pymole/cpp/CMakeLists.txt
pymole/cpp/__init__.py
pymole/cpp/operators.cpp
pymole/pure/__init__.py
pymole/pure/operators.py
pymole-0.1.0a0.dist-info/licenses/LICENSE
pymole-0.1.0a0.dist-info/METADATA
pymole-0.1.0a0.dist-info/WHEEL
pymole-0.1.0a0.dist-info/top_level.txt
pymole-0.1.0a0.dist-info/RECORD
