Metadata-Version: 2.4
Name: pymole
Version: 0.1.0a0
Summary: Python Mimetic Operators Library Enhanced
Author-email: Dilip Jain <59838651+Dilip-Jain@users.noreply.github.com>
License:                     GNU GENERAL PUBLIC LICENSE
Requires-Python: >=3.8
License-File: LICENSE
Requires-Dist: numpy>=1.20.0
Requires-Dist: scipy>=1.7.0
Provides-Extra: cpp
Requires-Dist: pybind11>=2.9.0; extra == "cpp"
Provides-Extra: test
Requires-Dist: pytest>=7.0.0; extra == "test"
Requires-Dist: pytest-cov>=3.0.0; extra == "test"
Dynamic: license-file
